spf_validator/__init__.py
spf_validator/validator.py
spf_validator-1.3.1.dist-info/licenses/LICENSE
spf_validator-1.3.1.dist-info/METADATA
spf_validator-1.3.1.dist-info/WHEEL
spf_validator-1.3.1.dist-info/top_level.txt
spf_validator-1.3.1.dist-info/RECORD
