Metadata-Version: 2.4
Name: spf_validator
Version: 1.3.1
Summary: Validates Sender Policy Framework (SPF) strings to ensure they are formatted correctly.
Author-email: Frank Corso <frank@frankcorso.me>
License: MIT License
Project-URL: Repository, https://github.com/fpcorso/spf-validator
Keywords: spf,sender policy framework,email
Requires-Python: >=3.9
License-File: LICENSE
Requires-Dist: dnspython<2.8,>=2.5
Dynamic: license-file
